klldPinger/__init__.py
klldPinger-1.0.7.dist-info/METADATA
klldPinger-1.0.7.dist-info/WHEEL
klldPinger-1.0.7.dist-info/top_level.txt
klldPinger-1.0.7.dist-info/RECORD
