Metadata-Version: 2.1
Name: klldPinger
Version: 1.0.7
Summary: Async Tool For Uploading URL's To klldPinger
Home-page: https://pinger.klld.tk/
Author: klld
License: UNKNOWN
Platform: UNKNOWN
Classifier: Programming Language :: Python :: 3
Classifier: License :: OSI Approved :: MIT License
Classifier: Operating System :: OS Independent
Requires-Dist: aiohttp
